EasyMath2/__init__.py
EasyMath2/module1.py
EasyMath2/module2.py
EasyMath1-0.1.dist-info/METADATA
EasyMath1-0.1.dist-info/WHEEL
EasyMath1-0.1.dist-info/top_level.txt
EasyMath1-0.1.dist-info/RECORD
